Workbook

Sheet instrucciones
A1: COPILOTO DE MARKETING IA · YANGO — Excel fuente del prototipo
A2: ESCENARIO ILUSTRATIVO: Escenario muy favorable. Métricas simuladas para análisis académico; no son resultados reales.
A3: Este archivo es la ÚNICA fuente de datos del prototipo. El prototipo lee las pestañas por su nombre y las columnas por su encabezado.
A5: CÓMO ACTUALIZARLO
A6: 1. datos_crudos: agrega una fila por canal y semana (Semana, Fecha inicio, Canal, Inversión, Impresiones, Clics, Conversiones, Ingresos atribuidos).
A7: Puedes agregar canales nuevos (p. ej. "TikTok Ads") o semanas nuevas: el prototipo toma por defecto la semana más reciente.
A8: 2. diccionario: define cada KPI (definición única, fórmula, dueño y meta). El asistente responde las definiciones desde aquí.
A9: 3. presupuesto: presupuesto planificado por mes (AAAA-MM) y canal. Se usa para el plan vs. real del briefing.
A10: 4. kpis: vista de control con fórmulas para la semana de la celda B1 (solo para personas; el prototipo recalcula todo desde datos_crudos).
A11: 5. log_ia: el prototipo permite descargar el registro de briefings y preguntas; puedes pegarlo aquí para auditar calidad y adopción.
A13: CÓMO VERLO EN EL PROTOTIPO
A14: Opción A (inmediata): en el prototipo pulsa "Cargar mi Excel" y elige este archivo editado. Todo se recalcula al instante en tu navegador.
... A20: • Datos ilustrativos para el prototipo académico (Innovación Tech III).

Sheet datos_crudos
A1: Semana | B1: Fecha inicio | C1: Canal | D1: Inversión (USD) | E1: Impresiones | F1: Clics | G1: Conversiones | H1: Ingresos atribuidos (USD)
A2: 39 | B2: 46286 | C2: Google Ads | D2: 165000 | E2: 2250000 | F2: 80719 | G2: 33825 | H2: 761062
A3: 39 | B3: 46286 | C3: Meta Ads | D3: 128000 | E3: 2850000 | F3: 97256 | G3: 24960 | H3: 561600
A4: 39 | B4: 46286 | C4: Yango Ads | D4: 82000 | E4: 1380000 | F4: 48300 | G4: 16400 | H4: 369000
A5: 40 | B5: 46293 | C5: Google Ads | D5: 170000 | E5: 2300000 | F5: 82513 | G5: 34850 | H5: 784125
A6: 40 | B6: 46293 | C6: Meta Ads | D6: 130000 | E6: 2900000 | F6: 98963 | G6: 25350 | H6: 570375
A7: 40 | B7: 46293 | C7: Yango Ads | D7: 85000 | E7: 1420000 | F7: 49700 | G7: 17000 | H7: 382500
A8: 41 | B8: 46300 | C8: Google Ads | D8: 175000 | E8: 2350000 | F8: 84306 | G8: 35875 | H8: 807187
A9: 41 | B9: 46300 | C9: Meta Ads | D9: 135000 | E9: 2950000 | F9: 100669 | G9: 26325 | H9: 592312
A10: 41 | B10: 46300 | C10: Yango Ads | D10: 88000 | E10: 1480000 | F10: 51800 | G10: 17600 | H10: 396000
A11: 42 | B11: 46307 | C11: Google Ads | D11: 180000 | E11: 2400000 | F11: 86100 | G11: 36900 | H11: 830250
A12: 42 | B12: 46307 | C12: Meta Ads | D12: 142000 | E12: 3100000 | F12: 105788 | G12: 27690 | H12: 623025
A13: 42 | B13: 46307 | C13: Yango Ads | D13: 90000 | E13: 1500000 | F13: 52500 | G13: 18000 | H13: 405000

Sheet kpis
A1: Semana | B1: =MAX(datos_crudos!A:A) | C1: ← cambia este número para ver otra semana (o deja la fórmula para la más reciente)
A3: Canal | B3: Inversión (USD) | C3: Conversiones | D3: Ingresos (USD) | E3: ROAS | F3: CPA (USD) | G3: CTR
A4: Google Ads | B4: =SUMIFS(datos_crudos!D:D,datos_crudos!$A:$A,$B$1,datos_crudos!$C:$C,$A4) | C4: =SUMIFS(datos_crudos!G:G,datos_crudos!$A:$A,$B$1,datos_crudos!$C:$C,$A4) | D4: =SUMIFS(datos_crudos!H:H,datos_crudos!$A:$A,$B$1,datos_crudos!$C:$C,$A4) | E4: =IFERROR(D4/B4,0) | F4: =IFERROR(B4/C4,0) | G4: =IFERROR(SUMIFS(datos_crudos!F:F,datos_crudos!$A:$A,$B$1,datos_crudos!$C:$C,$A4)/SUMIFS(datos_crudos!E:E,datos_crudos!$A:$A,$B$1,datos_crudos!$C:$C,$A4),0)
A5: Meta Ads | B5: =SUMIFS(datos_crudos!D:D,datos_crudos!$A:$A,$B$1,datos_crudos!$C:$C,$A5) | C5: =SUMIFS(datos_crudos!G:G,datos_crudos!$A:$A,$B$1,datos_crudos!$C:$C,$A5) | D5: =SUMIFS(datos_crudos!H:H,datos_crudos!$A:$A,$B$1,datos_crudos!$C:$C,$A5) | E5: =IFERROR(D5/B5,0) | F5: =IFERROR(B5/C5,0) | G5: =IFERROR(SUMIFS(datos_crudos!F:F,datos_crudos!$A:$A,$B$1,datos_crudos!$C:$C,$A5)/SUMIFS(datos_crudos!E:E,datos_crudos!$A:$A,$B$1,datos_crudos!$C:$C,$A5),0)
A6: Yango Ads | B6: =SUMIFS(datos_crudos!D:D,datos_crudos!$A:$A,$B$1,datos_crudos!$C:$C,$A6) | C6: =SUMIFS(datos_crudos!G:G,datos_crudos!$A:$A,$B$1,datos_crudos!$C:$C,$A6) | D6: =SUMIFS(datos_crudos!H:H,datos_crudos!$A:$A,$B$1,datos_crudos!$C:$C,$A6) | E6: =IFERROR(D6/B6,0) | F6: =IFERROR(B6/C6,0) | G6: =IFERROR(SUMIFS(datos_crudos!F:F,datos_crudos!$A:$A,$B$1,datos_crudos!$C:$C,$A6)/SUMIFS(datos_crudos!E:E,datos_crudos!$A:$A,$B$1,datos_crudos!$C:$C,$A6),0)
A7: Total | B7: =SUM(B4:B6) | C7: =SUM(C4:C6) | D7: =SUM(D4:D6) | E7: =IFERROR(D7/B7,0) | F7: =IFERROR(B7/C7,0) | G7: =IFERROR(SUMIFS(datos_crudos!F:F,datos_crudos!A:A,B1)/SUMIFS(datos_crudos!E:E,datos_crudos!A:A,B1),0)
A9: Vista de control para personas. Si agregas un canal nuevo, añade una fila aquí; el prototipo lo detecta solo desde datos_crudos.

Sheet diccionario
A1: KPI | B1: Definición única | C1: Fórmula | D1: Dueño | E1: Meta
A2: ROAS | B2: Retorno de la inversión publicitaria: ingresos atribuidos por cada dólar invertido. | C2: Ingresos atribuidos ÷ inversión | D2: Performance | E2: ≥ 3,0x
A3: CPA | B3: Costo por adquisición: cuánto cuesta cada conversión. | C3: Inversión ÷ conversiones | D3: Performance | E3: ≤ $8
A4: Conversión | B4: Pedido o viaje completado atribuido a una campaña. | C4: Conteo de pedidos o viajes completados | D4: Analista | E4: —
A5: CTR | B5: Porcentaje de impresiones que generan un clic. | C5: Clics ÷ impresiones | D5: Performance | E5: ≥ 2,5%
A6: Inversión | B6: Gasto en medios pagado a la plataforma en la semana (USD, sin impuestos). | C6: Suma del gasto reportado por la plataforma | D6: Analista | E6: Según presupuesto
A7: Ingresos atribuidos | B7: Ingresos de los pedidos o viajes atribuidos a campañas según el modelo de la plataforma. | C7: Suma de ingresos atribuidos | D7: Analista | E7: —

Sheet presupuesto
A1: Mes | B1: Canal | C1: Presupuesto (USD)
A2: 2026-09 | B2: Google Ads | C2: 720000
A3: 2026-09 | B3: Meta Ads | C3: 560000
A4: 2026-09 | B4: Yango Ads | C4: 350000
A5: 2026-10 | B5: Google Ads | C5: 760000
A6: 2026-10 | B6: Meta Ads | C6: 600000
A7: 2026-10 | B7: Yango Ads | C7: 380000

Sheet log_ia
A1: Fecha | B1: Tipo | C1: Semana | D1: Pregunta / briefing | E1: Respuesta | F1: Fuente | G1: Revisado por | H1: Decisión / feedback
